README.rst
setup.cfg
setup.py
num_shorty/__init__.py
num_shorty.egg-info/PKG-INFO
num_shorty.egg-info/SOURCES.txt
num_shorty.egg-info/dependency_links.txt
num_shorty.egg-info/not-zip-safe
num_shorty.egg-info/top_level.txt