Metadata-Version: 1.1
Name: num-shorty
Version: 1.0.1
Summary: Converts an integer to a hexdigest like string - except not 16 length but provided alphabet length
Home-page: UNKNOWN
Author: Matouš Höschl
Author-email: UNKNOWN
License: MIT
Download-URL: https://github.com/matousgit/num_shorty/archive/1.0.0.tar.gz
Platform: UNKNOWN
Classifier: Intended Audience :: Developers
Classifier: Natural Language :: English
Classifier: Programming Language :: Python :: 3.7
